{
  "TranslationProperties": {
    "Name": "irai.items.Socket_Puncher.name",
    "Description": "irai.items.Socket_Puncher.description"
  },
  "Icon": "Icons/ItemsGenerated/Ingredient_Stud_Iron.png",
  "Categories": [
    "Items.Ingredients"
  ],
  "Recipe": {
    "Input": [
      {
        "ItemId": "Ingredient_Bar_Iron",
        "Quantity": 1
      }
    ],
    "BenchRequirement": [
      {
        "Type": "Processing",
        "Id": "Salvagebench"
      }
    ],
    "OutputQuantity": 15,
    "TimeSeconds": 3
  },
  "MaxStack": 100,
  "ItemLevel": 1,
  "ItemSoundSetId": "ISS_Items_Ingots",
  "Tags": {
    "Type": [
      "SocketMaterial"
    ]
  }
}
